LICENSE
README.md
setup.cfg
setup.py
cBCI/__init__.py
cBCI.egg-info/PKG-INFO
cBCI.egg-info/SOURCES.txt
cBCI.egg-info/dependency_links.txt
cBCI.egg-info/requires.txt
cBCI.egg-info/top_level.txt
cBCI/groups/__init__.py
cBCI/groups/performance.py
cBCI/individual/__init__.py
cBCI/individual/performance.py
cBCI/plotting/__init__.py
cBCI/plotting/accuracy.py
examples/__init__.py
examples/metacognition.py
examples/target_detection.py