Metadata-Version: 2.1
Name: cBCI
Version: 0.1.0
Summary: The Collaborative Brain-Computer Interface Toolbox
Home-page: https://github.com/davidevaleriani/cBCI
Author: Davide Valeriani
Author-email: davide.valeriani@gmail.com
Classifier: Programming Language :: Python
Classifier: Topic :: Scientific/Engineering :: Human Machine Interfaces
Classifier: Topic :: Scientific/Engineering :: Artificial Intelligence
Classifier: Intended Audience :: Science/Research
Classifier: License :: OSI Approved :: MIT License
Classifier: Operating System :: OS Independent
License-File: LICENSE
